smart_tagger/__init__.py
smart_tagger/__main__.py
smart_tagger/music.py
smart_tagger/utils.py
smart_tagger-0.1.0.dist-info/METADATA
smart_tagger-0.1.0.dist-info/WHEEL
smart_tagger-0.1.0.dist-info/licenses/LICENSE
smart_tagger-0.1.0.dist-info/RECORD
