Metadata-Version: 2.3
Name: smart-tagger
Version: 0.1.0
Summary: Python utility for editing tags in media files
Project-URL: homepage, https://github.com/Pavel-Sushko/smart-tagger
Project-URL: issues, https://github.com/Pavel-Sushko/smart-tagger/issues
Author-email: Pavel Sushko <github@psushko.com>
License-File: LICENSE
Classifier: Development Status :: 1 - Planning
Classifier: Environment :: Console
Classifier: Intended Audience :: End Users/Desktop
Classifier: License :: OSI Approved :: MIT License
Classifier: Operating System :: MacOS :: MacOS X
Classifier: Operating System :: Microsoft :: Windows
Classifier: Operating System :: POSIX :: Linux
Classifier: Programming Language :: Python :: 3
Classifier: Programming Language :: Python :: 3 :: Only
Classifier: Programming Language :: Python :: 3.11
Classifier: Programming Language :: Python :: 3.12
Requires-Python: >=3.11
Requires-Dist: tinytag
